
{
    "hero_title": "আমাদের সম্পর্কে",
    "hero_subtitle": "আপনার সফলতার পথে, আমরা আপনার বিশ্বস্ত সঙ্গী। SkillShikhun-এ আমরা প্রযুক্তির মাধ্যমে আপনার স্বপ্ন পূরণে সহায়তা করি।",
    "story_tagline": "আমাদের পথচলা",
    "story_heading": "আপনার সফলতার পথে, আমরা আপনার বিশ্বস্ত সঙ্গী।",
    "story_description_1": "SkillShikhun একটি শীর্ষস্থানীয় আইটি প্রশিক্ষণ কেন্দ্র যেখানে আমরা শিক্ষার্থীদের প্রযুক্তিগত জ্ঞান এবং দক্ষতার মাধ্যমে তাদের স্বপ্ন পূরণে সহায়তা করি।",
    "story_description_2": "আমাদের লক্ষ্য হল দেশের প্রতিটি প্রান্তে মানসম্মত আইটি শিক্ষা পৌঁছে দেওয়া এবং একটি ডিজিটাল বাংলাদেশ গঠনে ভূমিকা রাখা। আমরা বিশ্বাস করি, সঠিক দক্ষতা অর্জনের মাধ্যমে যে কেউ নিজের পায়ে দাঁড়াতে পারে এবং দেশের অর্থনীতিতে অবদান রাখতে পারে।",
    "story_image": "https://img.freepik.com/premium-photo/education-technology-friendship-school-concept-smiling-male-student-with-classmates-computer-class_380164-79006.jpg?w=740",
    "vision_title": "আমাদের লক্ষ্য (Our Vision)",
    "vision_description": "বাংলাদেশের তরুণ প্রজন্মকে বিশ্বমানের প্রযুক্তিগত শিক্ষায় শিক্ষিত করে একটি দক্ষ ও স্বনির্ভর জাতি হিসেবে গড়ে তোলা, যেখানে প্রত্যেকেই ডিজিটাল অর্থনীতির অংশীদার হবে।",
    "mission_title": "আমাদের উদ্দেশ্য (Our Mission)",
    "mission_description": "সাশ্রয়ী মূল্যে মানসম্মত ও practically আইটি প্রশিক্ষণ প্রদান করা। শিক্ষার্থীদের জন্য সার্বক্ষণিক সাপোর্ট নিশ্চিত করা এবং ক্যারিয়ার গড়তে প্রয়োজনীয় গাইডলাইন প্রদান করা।",
    "stats_heading": "এক নজরে SkillShikhun",
    "stats_subheading": "আমরা যা অর্জন করেছি এবং যা নিয়ে আমরা গর্বিত",
    "stats": [
      { "value": "1k+", "label": "সফল শিক্ষার্থী" },
      { "value": "5+", "label": "দক্ষ প্রশিক্ষক" },
      { "value": "10+", "label": "অ্যাক্টিভ কোর্স" },
      { "value": "95%", "label": "সফলতার হার" }
    ]
}
